square_root.sv
module square_root(input logic [31:0] op, input reg clk, reset, output logic [31:0] result,output logic flag);
    logic [31:0] cnt,add,sqr;
    logic inreset;

    always_ff @(posedge clk) begin //reset parameters
        if (reset || flag) begin
            cnt<=32'b1;
            add<=32'b11;
            sqr<=32'b1;
            flag<=0;  //A flag - indicates if the algo is done
        end
        else
            if(sqr<op) begin //itertaion - algorithm not finished
                cnt<=cnt+32'b01;
                add<=add+32'b10;
                sqr<=sqr+add;S
                flag<=0;
        end
            else if (sqr==op) begin //op has an intejer square root
                result<=cnt;  
                flag<=1; 
            end
            else begin // op's sqaure root has a decimal point, round down
                result<=cnt-1;
                flag<=1;
            end

    end     
endmodule

sqr_rt_TB.sv
module sqr_rt_tb();
    logic [31:0] op,result;
    logic clk,rst,flag;

    square_root DUT(.op(op),.result(result),.clk(clk),.reset(rst),.flag(flag));

    always #5 clk = ~clk; 
    initial begin
        $dumpfile("test_sqr.vcd");
        $dumpvars(0,sqr_rt_tb);
         
        op = 32'd63504;
        assert (op[31]==0) begin //make sure the operand is positive
            rst = 1;
            clk = 0;
            #10;
            rst = 0;

            wait(flag == 1'b1); //wait for the algorithm to finish
            $display("The square root of %d is %d",op, result);
        end
        else
            $display("The operand is negative");
        $finish;
    end
endmodule

test_sqr.vcd
$date
	Thu Apr 09 19:37:34 2026
$end
$version
	Icarus Verilog
$end
$timescale
	1s
$end
$scope module sqr_rt_tb $end
$var wire 32 ! result [31:0] $end
$var wire 1 " flag $end
$var reg 1 # clk $end
$var reg 32 $ op [31:0] $end
$var reg 1 % rst $end
$scope module DUT $end
$var wire 1 # clk $end
$var wire 32 & op [31:0] $end
$var wire 1 % reset $end
$var reg 32 ' add [31:0] $end
$var reg 32 ( cnt [31:0] $end
$var reg 1 " flag $end
$var reg 32 ) result [31:0] $end
$var reg 32 * sqr [31:0] $end
$upscope $end
$upscope $end
$enddefinitions $end
$comment Show the parameter values. $end
$dumpall
$end
#0
$dumpvars
bx *
bx )
bx (
bx '
b1111100000010000 &
1%
b1111100000010000 $
0#
x"
bx !
$end
#5
0"
b1 *
b11 '
b1 (
1#
#10
0#
0%
#15
b100 *
b101 '
b10 (
1#
#20
0#
#25
b1001 *
b111 '
b11 (
1#
#30
0#
#35
b10000 *
b1001 '
b100 (
1#
#40
0#
#45
b11001 *
b1011 '
b101 (
1#
#50
0#
#55
b100100 *
b1101 '
b110 (
1#
#60
0#
#65
b110001 *
b1111 '
b111 (
1#
#70
0#
#75
b1000000 *
b10001 '
b1000 (
1#
#80
0#
#85
b1010001 *
b10011 '
b1001 (
1#
#90
0#
#95
b1100100 *
b10101 '
b1010 (
1#
#100
0#
#105
b1111001 *
b10111 '
b1011 (
1#
#110
0#
#115
b10010000 *
b11001 '
b1100 (
1#
#120
0#
#125
b10101001 *
b11011 '
b1101 (
1#
#130
0#
#135
b11000100 *
b11101 '
b1110 (
1#
#140
0#
#145
b11100001 *
b11111 '
b1111 (
1#
#150
0#
#155
b100000000 *
b100001 '
b10000 (
1#
#160
0#
#165
b100100001 *
b100011 '
b10001 (
1#
#170
0#
#175
b101000100 *
b100101 '
b10010 (
1#
#180
0#
#185
b101101001 *
b100111 '
b10011 (
1#
#190
0#
#195
b110010000 *
b101001 '
b10100 (
1#
#200
0#
#205
b110111001 *
b101011 '
b10101 (
1#
#210
0#
#215
b111100100 *
b101101 '
b10110 (
1#
#220
0#
#225
b1000010001 *
b101111 '
b10111 (
1#
#230
0#
#235
b1001000000 *
b110001 '
b11000 (
1#
#240
0#
#245
b1001110001 *
b110011 '
b11001 (
1#
#250
0#
#255
b1010100100 *
b110101 '
b11010 (
1#
#260
0#
#265
b1011011001 *
b110111 '
b11011 (
1#
#270
0#
#275
b1100010000 *
b111001 '
b11100 (
1#
#280
0#
#285
b1101001001 *
b111011 '
b11101 (
1#
#290
0#
#295
b1110000100 *
b111101 '
b11110 (
1#
#300
0#
#305
b1111000001 *
b111111 '
b11111 (
1#
#310
0#
#315
b10000000000 *
b1000001 '
b100000 (
1#
#320
0#
#325
b10001000001 *
b1000011 '
b100001 (
1#
#330
0#
#335
b10010000100 *
b1000101 '
b100010 (
1#
#340
0#
#345
b10011001001 *
b1000111 '
b100011 (
1#
#350
0#
#355
b10100010000 *
b1001001 '
b100100 (
1#
#360
0#
#365
b10101011001 *
b1001011 '
b100101 (
1#
#370
0#
#375
b10110100100 *
b1001101 '
b100110 (
1#
#380
0#
#385
b10111110001 *
b1001111 '
b100111 (
1#
#390
0#
#395
b11001000000 *
b1010001 '
b101000 (
1#
#400
0#
#405
b11010010001 *
b1010011 '
b101001 (
1#
#410
0#
#415
b11011100100 *
b1010101 '
b101010 (
1#
#420
0#
#425
b11100111001 *
b1010111 '
b101011 (
1#
#430
0#
#435
b11110010000 *
b1011001 '
b101100 (
1#
#440
0#
#445
b11111101001 *
b1011011 '
b101101 (
1#
#450
0#
#455
b100001000100 *
b1011101 '
b101110 (
1#
#460
0#
#465
b100010100001 *
b1011111 '
b101111 (
1#
#470
0#
#475
b100100000000 *
b1100001 '
b110000 (
1#
#480
0#
#485
b100101100001 *
b1100011 '
b110001 (
1#
#490
0#
#495
b100111000100 *
b1100101 '
b110010 (
1#
#500
0#
#505
b101000101001 *
b1100111 '
b110011 (
1#
#510
0#
#515
b101010010000 *
b1101001 '
b110100 (
1#
#520
0#
#525
b101011111001 *
b1101011 '
b110101 (
1#
#530
0#
#535
b101101100100 *
b1101101 '
b110110 (
1#
#540
0#
#545
b101111010001 *
b1101111 '
b110111 (
1#
#550
0#
#555
b110001000000 *
b1110001 '
b111000 (
1#
#560
0#
#565
b110010110001 *
b1110011 '
b111001 (
1#
#570
0#
#575
b110100100100 *
b1110101 '
b111010 (
1#
#580
0#
#585
b110110011001 *
b1110111 '
b111011 (
1#
#590
0#
#595
b111000010000 *
b1111001 '
b111100 (
1#
#600
0#
#605
b111010001001 *
b1111011 '
b111101 (
1#
#610
0#
#615
b111100000100 *
b1111101 '
b111110 (
1#
#620
0#
#625
b111110000001 *
b1111111 '
b111111 (
1#
#630
0#
#635
b1000000000000 *
b10000001 '
b1000000 (
1#
#640
0#
#645
b1000010000001 *
b10000011 '
b1000001 (
1#
#650
0#
#655
b1000100000100 *
b10000101 '
b1000010 (
1#
#660
0#
#665
b1000110001001 *
b10000111 '
b1000011 (
1#
#670
0#
#675
b1001000010000 *
b10001001 '
b1000100 (
1#
#680
0#
#685
b1001010011001 *
b10001011 '
b1000101 (
1#
#690
0#
#695
b1001100100100 *
b10001101 '
b1000110 (
1#
#700
0#
#705
b1001110110001 *
b10001111 '
b1000111 (
1#
#710
0#
#715
b1010001000000 *
b10010001 '
b1001000 (
1#
#720
0#
#725
b1010011010001 *
b10010011 '
b1001001 (
1#
#730
0#
#735
b1010101100100 *
b10010101 '
b1001010 (
1#
#740
0#
#745
b1010111111001 *
b10010111 '
b1001011 (
1#
#750
0#
#755
b1011010010000 *
b10011001 '
b1001100 (
1#
#760
0#
#765
b1011100101001 *
b10011011 '
b1001101 (
1#
#770
0#
#775
b1011111000100 *
b10011101 '
b1001110 (
1#
#780
0#
#785
b1100001100001 *
b10011111 '
b1001111 (
1#
#790
0#
#795
b1100100000000 *
b10100001 '
b1010000 (
1#
#800
0#
#805
b1100110100001 *
b10100011 '
b1010001 (
1#
#810
0#
#815
b1101001000100 *
b10100101 '
b1010010 (
1#
#820
0#
#825
b1101011101001 *
b10100111 '
b1010011 (
1#
#830
0#
#835
b1101110010000 *
b10101001 '
b1010100 (
1#
#840
0#
#845
b1110000111001 *
b10101011 '
b1010101 (
1#
#850
0#
#855
b1110011100100 *
b10101101 '
b1010110 (
1#
#860
0#
#865
b1110110010001 *
b10101111 '
b1010111 (
1#
#870
0#
#875
b1111001000000 *
b10110001 '
b1011000 (
1#
#880
0#
#885
b1111011110001 *
b10110011 '
b1011001 (
1#
#890
0#
#895
b1111110100100 *
b10110101 '
b1011010 (
1#
#900
0#
#905
b10000001011001 *
b10110111 '
b1011011 (
1#
#910
0#
#915
b10000100010000 *
b10111001 '
b1011100 (
1#
#920
0#
#925
b10000111001001 *
b10111011 '
b1011101 (
1#
#930
0#
#935
b10001010000100 *
b10111101 '
b1011110 (
1#
#940
0#
#945
b10001101000001 *
b10111111 '
b1011111 (
1#
#950
0#
#955
b10010000000000 *
b11000001 '
b1100000 (
1#
#960
0#
#965
b10010011000001 *
b11000011 '
b1100001 (
1#
#970
0#
#975
b10010110000100 *
b11000101 '
b1100010 (
1#
#980
0#
#985
b10011001001001 *
b11000111 '
b1100011 (
1#
#990
0#
#995
b10011100010000 *
b11001001 '
b1100100 (
1#
#1000
0#
#1005
b10011111011001 *
b11001011 '
b1100101 (
1#
#1010
0#
#1015
b10100010100100 *
b11001101 '
b1100110 (
1#
#1020
0#
#1025
b10100101110001 *
b11001111 '
b1100111 (
1#
#1030
0#
#1035
b10101001000000 *
b11010001 '
b1101000 (
1#
#1040
0#
#1045
b10101100010001 *
b11010011 '
b1101001 (
1#
#1050
0#
#1055
b10101111100100 *
b11010101 '
b1101010 (
1#
#1060
0#
#1065
b10110010111001 *
b11010111 '
b1101011 (
1#
#1070
0#
#1075
b10110110010000 *
b11011001 '
b1101100 (
1#
#1080
0#
#1085
b10111001101001 *
b11011011 '
b1101101 (
1#
#1090
0#
#1095
b10111101000100 *
b11011101 '
b1101110 (
1#
#1100
0#
#1105
b11000000100001 *
b11011111 '
b1101111 (
1#
#1110
0#
#1115
b11000100000000 *
b11100001 '
b1110000 (
1#
#1120
0#
#1125
b11000111100001 *
b11100011 '
b1110001 (
1#
#1130
0#
#1135
b11001011000100 *
b11100101 '
b1110010 (
1#
#1140
0#
#1145
b11001110101001 *
b11100111 '
b1110011 (
1#
#1150
0#
#1155
b11010010010000 *
b11101001 '
b1110100 (
1#
#1160
0#
#1165
b11010101111001 *
b11101011 '
b1110101 (
1#
#1170
0#
#1175
b11011001100100 *
b11101101 '
b1110110 (
1#
#1180
0#
#1185
b11011101010001 *
b11101111 '
b1110111 (
1#
#1190
0#
#1195
b11100001000000 *
b11110001 '
b1111000 (
1#
#1200
0#
#1205
b11100100110001 *
b11110011 '
b1111001 (
1#
#1210
0#
#1215
b11101000100100 *
b11110101 '
b1111010 (
1#
#1220
0#
#1225
b11101100011001 *
b11110111 '
b1111011 (
1#
#1230
0#
#1235
b11110000010000 *
b11111001 '
b1111100 (
1#
#1240
0#
#1245
b11110100001001 *
b11111011 '
b1111101 (
1#
#1250
0#
#1255
b11111000000100 *
b11111101 '
b1111110 (
1#
#1260
0#
#1265
b11111100000001 *
b11111111 '
b1111111 (
1#
#1270
0#
#1275
b100000000000000 *
b100000001 '
b10000000 (
1#
#1280
0#
#1285
b100000100000001 *
b100000011 '
b10000001 (
1#
#1290
0#
#1295
b100001000000100 *
b100000101 '
b10000010 (
1#
#1300
0#
#1305
b100001100001001 *
b100000111 '
b10000011 (
1#
#1310
0#
#1315
b100010000010000 *
b100001001 '
b10000100 (
1#
#1320
0#
#1325
b100010100011001 *
b100001011 '
b10000101 (
1#
#1330
0#
#1335
b100011000100100 *
b100001101 '
b10000110 (
1#
#1340
0#
#1345
b100011100110001 *
b100001111 '
b10000111 (
1#
#1350
0#
#1355
b100100001000000 *
b100010001 '
b10001000 (
1#
#1360
0#
#1365
b100100101010001 *
b100010011 '
b10001001 (
1#
#1370
0#
#1375
b100101001100100 *
b100010101 '
b10001010 (
1#
#1380
0#
#1385
b100101101111001 *
b100010111 '
b10001011 (
1#
#1390
0#
#1395
b100110010010000 *
b100011001 '
b10001100 (
1#
#1400
0#
#1405
b100110110101001 *
b100011011 '
b10001101 (
1#
#1410
0#
#1415
b100111011000100 *
b100011101 '
b10001110 (
1#
#1420
0#
#1425
b100111111100001 *
b100011111 '
b10001111 (
1#
#1430
0#
#1435
b101000100000000 *
b100100001 '
b10010000 (
1#
#1440
0#
#1445
b101001000100001 *
b100100011 '
b10010001 (
1#
#1450
0#
#1455
b101001101000100 *
b100100101 '
b10010010 (
1#
#1460
0#
#1465
b101010001101001 *
b100100111 '
b10010011 (
1#
#1470
0#
#1475
b101010110010000 *
b100101001 '
b10010100 (
1#
#1480
0#
#1485
b101011010111001 *
b100101011 '
b10010101 (
1#
#1490
0#
#1495
b101011111100100 *
b100101101 '
b10010110 (
1#
#1500
0#
#1505
b101100100010001 *
b100101111 '
b10010111 (
1#
#1510
0#
#1515
b101101001000000 *
b100110001 '
b10011000 (
1#
#1520
0#
#1525
b101101101110001 *
b100110011 '
b10011001 (
1#
#1530
0#
#1535
b101110010100100 *
b100110101 '
b10011010 (
1#
#1540
0#
#1545
b101110111011001 *
b100110111 '
b10011011 (
1#
#1550
0#
#1555
b101111100010000 *
b100111001 '
b10011100 (
1#
#1560
0#
#1565
b110000001001001 *
b100111011 '
b10011101 (
1#
#1570
0#
#1575
b110000110000100 *
b100111101 '
b10011110 (
1#
#1580
0#
#1585
b110001011000001 *
b100111111 '
b10011111 (
1#
#1590
0#
#1595
b110010000000000 *
b101000001 '
b10100000 (
1#
#1600
0#
#1605
b110010101000001 *
b101000011 '
b10100001 (
1#
#1610
0#
#1615
b110011010000100 *
b101000101 '
b10100010 (
1#
#1620
0#
#1625
b110011111001001 *
b101000111 '
b10100011 (
1#
#1630
0#
#1635
b110100100010000 *
b101001001 '
b10100100 (
1#
#1640
0#
#1645
b110101001011001 *
b101001011 '
b10100101 (
1#
#1650
0#
#1655
b110101110100100 *
b101001101 '
b10100110 (
1#
#1660
0#
#1665
b110110011110001 *
b101001111 '
b10100111 (
1#
#1670
0#
#1675
b110111001000000 *
b101010001 '
b10101000 (
1#
#1680
0#
#1685
b110111110010001 *
b101010011 '
b10101001 (
1#
#1690
0#
#1695
b111000011100100 *
b101010101 '
b10101010 (
1#
#1700
0#
#1705
b111001000111001 *
b101010111 '
b10101011 (
1#
#1710
0#
#1715
b111001110010000 *
b101011001 '
b10101100 (
1#
#1720
0#
#1725
b111010011101001 *
b101011011 '
b10101101 (
1#
#1730
0#
#1735
b111011001000100 *
b101011101 '
b10101110 (
1#
#1740
0#
#1745
b111011110100001 *
b101011111 '
b10101111 (
1#
#1750
0#
#1755
b111100100000000 *
b101100001 '
b10110000 (
1#
#1760
0#
#1765
b111101001100001 *
b101100011 '
b10110001 (
1#
#1770
0#
#1775
b111101111000100 *
b101100101 '
b10110010 (
1#
#1780
0#
#1785
b111110100101001 *
b101100111 '
b10110011 (
1#
#1790
0#
#1795
b111111010010000 *
b101101001 '
b10110100 (
1#
#1800
0#
#1805
b111111111111001 *
b101101011 '
b10110101 (
1#
#1810
0#
#1815
b1000000101100100 *
b101101101 '
b10110110 (
1#
#1820
0#
#1825
b1000001011010001 *
b101101111 '
b10110111 (
1#
#1830
0#
#1835
b1000010001000000 *
b101110001 '
b10111000 (
1#
#1840
0#
#1845
b1000010110110001 *
b101110011 '
b10111001 (
1#
#1850
0#
#1855
b1000011100100100 *
b101110101 '
b10111010 (
1#
#1860
0#
#1865
b1000100010011001 *
b101110111 '
b10111011 (
1#
#1870
0#
#1875
b1000101000010000 *
b101111001 '
b10111100 (
1#
#1880
0#
#1885
b1000101110001001 *
b101111011 '
b10111101 (
1#
#1890
0#
#1895
b1000110100000100 *
b101111101 '
b10111110 (
1#
#1900
0#
#1905
b1000111010000001 *
b101111111 '
b10111111 (
1#
#1910
0#
#1915
b1001000000000000 *
b110000001 '
b11000000 (
1#
#1920
0#
#1925
b1001000110000001 *
b110000011 '
b11000001 (
1#
#1930
0#
#1935
b1001001100000100 *
b110000101 '
b11000010 (
1#
#1940
0#
#1945
b1001010010001001 *
b110000111 '
b11000011 (
1#
#1950
0#
#1955
b1001011000010000 *
b110001001 '
b11000100 (
1#
#1960
0#
#1965
b1001011110011001 *
b110001011 '
b11000101 (
1#
#1970
0#
#1975
b1001100100100100 *
b110001101 '
b11000110 (
1#
#1980
0#
#1985
b1001101010110001 *
b110001111 '
b11000111 (
1#
#1990
0#
#1995
b1001110001000000 *
b110010001 '
b11001000 (
1#
#2000
0#
#2005
b1001110111010001 *
b110010011 '
b11001001 (
1#
#2010
0#
#2015
b1001111101100100 *
b110010101 '
b11001010 (
1#
#2020
0#
#2025
b1010000011111001 *
b110010111 '
b11001011 (
1#
#2030
0#
#2035
b1010001010010000 *
b110011001 '
b11001100 (
1#
#2040
0#
#2045
b1010010000101001 *
b110011011 '
b11001101 (
1#
#2050
0#
#2055
b1010010111000100 *
b110011101 '
b11001110 (
1#
#2060
0#
#2065
b1010011101100001 *
b110011111 '
b11001111 (
1#
#2070
0#
#2075
b1010100100000000 *
b110100001 '
b11010000 (
1#
#2080
0#
#2085
b1010101010100001 *
b110100011 '
b11010001 (
1#
#2090
0#
#2095
b1010110001000100 *
b110100101 '
b11010010 (
1#
#2100
0#
#2105
b1010110111101001 *
b110100111 '
b11010011 (
1#
#2110
0#
#2115
b1010111110010000 *
b110101001 '
b11010100 (
1#
#2120
0#
#2125
b1011000100111001 *
b110101011 '
b11010101 (
1#
#2130
0#
#2135
b1011001011100100 *
b110101101 '
b11010110 (
1#
#2140
0#
#2145
b1011010010010001 *
b110101111 '
b11010111 (
1#
#2150
0#
#2155
b1011011001000000 *
b110110001 '
b11011000 (
1#
#2160
0#
#2165
b1011011111110001 *
b110110011 '
b11011001 (
1#
#2170
0#
#2175
b1011100110100100 *
b110110101 '
b11011010 (
1#
#2180
0#
#2185
b1011101101011001 *
b110110111 '
b11011011 (
1#
#2190
0#
#2195
b1011110100010000 *
b110111001 '
b11011100 (
1#
#2200
0#
#2205
b1011111011001001 *
b110111011 '
b11011101 (
1#
#2210
0#
#2215
b1100000010000100 *
b110111101 '
b11011110 (
1#
#2220
0#
#2225
b1100001001000001 *
b110111111 '
b11011111 (
1#
#2230
0#
#2235
b1100010000000000 *
b111000001 '
b11100000 (
1#
#2240
0#
#2245
b1100010111000001 *
b111000011 '
b11100001 (
1#
#2250
0#
#2255
b1100011110000100 *
b111000101 '
b11100010 (
1#
#2260
0#
#2265
b1100100101001001 *
b111000111 '
b11100011 (
1#
#2270
0#
#2275
b1100101100010000 *
b111001001 '
b11100100 (
1#
#2280
0#
#2285
b1100110011011001 *
b111001011 '
b11100101 (
1#
#2290
0#
#2295
b1100111010100100 *
b111001101 '
b11100110 (
1#
#2300
0#
#2305
b1101000001110001 *
b111001111 '
b11100111 (
1#
#2310
0#
#2315
b1101001001000000 *
b111010001 '
b11101000 (
1#
#2320
0#
#2325
b1101010000010001 *
b111010011 '
b11101001 (
1#
#2330
0#
#2335
b1101010111100100 *
b111010101 '
b11101010 (
1#
#2340
0#
#2345
b1101011110111001 *
b111010111 '
b11101011 (
1#
#2350
0#
#2355
b1101100110010000 *
b111011001 '
b11101100 (
1#
#2360
0#
#2365
b1101101101101001 *
b111011011 '
b11101101 (
1#
#2370
0#
#2375
b1101110101000100 *
b111011101 '
b11101110 (
1#
#2380
0#
#2385
b1101111100100001 *
b111011111 '
b11101111 (
1#
#2390
0#
#2395
b1110000100000000 *
b111100001 '
b11110000 (
1#
#2400
0#
#2405
b1110001011100001 *
b111100011 '
b11110001 (
1#
#2410
0#
#2415
b1110010011000100 *
b111100101 '
b11110010 (
1#
#2420
0#
#2425
b1110011010101001 *
b111100111 '
b11110011 (
1#
#2430
0#
#2435
b1110100010010000 *
b111101001 '
b11110100 (
1#
#2440
0#
#2445
b1110101001111001 *
b111101011 '
b11110101 (
1#
#2450
0#
#2455
b1110110001100100 *
b111101101 '
b11110110 (
1#
#2460
0#
#2465
b1110111001010001 *
b111101111 '
b11110111 (
1#
#2470
0#
#2475
b1111000001000000 *
b111110001 '
b11111000 (
1#
#2480
0#
#2485
b1111001000110001 *
b111110011 '
b11111001 (
1#
#2490
0#
#2495
b1111010000100100 *
b111110101 '
b11111010 (
1#
#2500
0#
#2505
b1111011000011001 *
b111110111 '
b11111011 (
1#
#2510
0#
#2515
b1111100000010000 *
b111111001 '
b11111100 (
1#
#2520
0#
#2525
1"
b11111100 !
b11111100 )
1#
